healthcare_ai_guardrails/__init__.py
healthcare_ai_guardrails/cli.py
healthcare_ai_guardrails/config.py
healthcare_ai_guardrails/runner.py
healthcare_ai_guardrails/testing/dicom_factory.py
healthcare_ai_guardrails/validators/basic.py
healthcare_ai_guardrails/validators/dicom.py
healthcare_ai_guardrails/validators/generic_dicom.py
healthcare_ai_guardrails/validators/schema.py
healthcare_ai_guardrails-0.2.0.dist-info/licenses/LICENSE
healthcare_ai_guardrails-0.2.0.dist-info/METADATA
healthcare_ai_guardrails-0.2.0.dist-info/WHEEL
healthcare_ai_guardrails-0.2.0.dist-info/entry_points.txt
healthcare_ai_guardrails-0.2.0.dist-info/top_level.txt
healthcare_ai_guardrails-0.2.0.dist-info/RECORD
