Metadata-Version: 2.4
Name: healthcare-ai-guardrails
Version: 0.2.0
Summary: Guardrails for AI input/output validation in healthcare, with DICOM support
Author-email: Sam Ingram <sampingram12@gmail.com>
License: MIT License
Project-URL: Homepage, https://github.com/SamPIngram/healthcare-ai-guardrails
Project-URL: Issues, https://github.com/SamPIngram/healthcare-ai-guardrails/issues
Keywords: AI,ML,Healthcare,DICOM,Validation,Guardrails
Classifier: Programming Language :: Python :: 3
Classifier: License :: OSI Approved :: MIT License
Classifier: Operating System :: OS Independent
Classifier: Intended Audience :: Healthcare Industry
Classifier: Topic :: Scientific/Engineering :: Medical Science Apps.
Requires-Python: >=3.9
License-File: LICENSE
Requires-Dist: pydicom>=2.3
Requires-Dist: PyYAML>=6.0
Requires-Dist: jsonschema>=4.20
Requires-Dist: numpy>=1.22
Provides-Extra: test
Requires-Dist: pytest>=8.4.2; extra == "test"
Provides-Extra: lint
Requires-Dist: ruff; extra == "lint"
Requires-Dist: black; extra == "lint"
Dynamic: license-file
